rsort/__init__.py
rsort/main.py
rsort/py.typed
rsort/requirements.py
rsort-0.1.2.dist-info/entry_points.txt
rsort-0.1.2.dist-info/LICENSE
rsort-0.1.2.dist-info/WHEEL
rsort-0.1.2.dist-info/METADATA
rsort-0.1.2.dist-info/RECORD
